[
  {
    "ScientificName": "Trachyrhamphus bicoarctatus",
    "SpecCode": "5981",
    "CommonName": "Bentstick pipefish",
    "Environments": [
      "salt"
    ],
    "Subspecies": []
  },
  {
    "ScientificName": "Trachyrhamphus longirostris",
    "SpecCode": "23124",
    "CommonName": "Itohikiyôji",
    "Environments": [
      "salt"
    ],
    "Subspecies": []
  },
  {
    "ScientificName": "Trachyrhamphus serratus",
    "SpecCode": "23123",
    "CommonName": "Cá Chìa vôi mõm răng cưa",
    "Environments": [
      "salt"
    ],
    "Subspecies": []
  }
]