{
  "Family": "Rivulidae",
  "Order": "Cyprinodontiformes",
  "Common": "Rivulines",
  "Genera": [
    {
      "Genus": "Anablepsoides",
      "SpeciesCount": 55,
      "genus_path": "genera/rivulidae/anablepsoides.json"
    },
    {
      "Genus": "Aphyolebias",
      "SpeciesCount": 8,
      "genus_path": "genera/rivulidae/aphyolebias.json"
    },
    {
      "Genus": "Atlantirivulus",
      "SpeciesCount": 15,
      "genus_path": "genera/rivulidae/atlantirivulus.json"
    },
    {
      "Genus": "Austrofundulus",
      "SpeciesCount": 7,
      "genus_path": "genera/rivulidae/austrofundulus.json"
    },
    {
      "Genus": "Austrolebias",
      "SpeciesCount": 55,
      "genus_path": "genera/rivulidae/austrolebias.json"
    },
    {
      "Genus": "Campellolebias",
      "SpeciesCount": 4,
      "genus_path": "genera/rivulidae/campellolebias.json"
    },
    {
      "Genus": "Cynodonichthys",
      "SpeciesCount": 27,
      "genus_path": "genera/rivulidae/cynodonichthys.json"
    },
    {
      "Genus": "Cynolebias",
      "SpeciesCount": 22,
      "genus_path": "genera/rivulidae/cynolebias.json"
    },
    {
      "Genus": "Cynopoecilus",
      "SpeciesCount": 6,
      "genus_path": "genera/rivulidae/cynopoecilus.json"
    },
    {
      "Genus": "Hypsolebias",
      "SpeciesCount": 41,
      "genus_path": "genera/rivulidae/hypsolebias.json"
    },
    {
      "Genus": "Kryptolebias",
      "SpeciesCount": 8,
      "genus_path": "genera/rivulidae/kryptolebias.json"
    },
    {
      "Genus": "Laimosemion",
      "SpeciesCount": 29,
      "genus_path": "genera/rivulidae/laimosemion.json"
    },
    {
      "Genus": "Leptolebias",
      "SpeciesCount": 6,
      "genus_path": "genera/rivulidae/leptolebias.json"
    },
    {
      "Genus": "Llanolebias",
      "SpeciesCount": 1,
      "genus_path": "genera/rivulidae/llanolebias.json"
    },
    {
      "Genus": "Maratecoara",
      "SpeciesCount": 4,
      "genus_path": "genera/rivulidae/maratecoara.json"
    },
    {
      "Genus": "Melanorivulus",
      "SpeciesCount": 51,
      "genus_path": "genera/rivulidae/melanorivulus.json"
    },
    {
      "Genus": "Micromoema",
      "SpeciesCount": 1,
      "genus_path": "genera/rivulidae/micromoema.json"
    },
    {
      "Genus": "Millerichthys",
      "SpeciesCount": 1,
      "genus_path": "genera/rivulidae/millerichthys.json"
    },
    {
      "Genus": "Moema",
      "SpeciesCount": 14,
      "genus_path": "genera/rivulidae/moema.json"
    },
    {
      "Genus": "Mucurilebias",
      "SpeciesCount": 1,
      "genus_path": "genera/rivulidae/mucurilebias.json"
    },
    {
      "Genus": "Nematolebias",
      "SpeciesCount": 3,
      "genus_path": "genera/rivulidae/nematolebias.json"
    },
    {
      "Genus": "Neofundulus",
      "SpeciesCount": 8,
      "genus_path": "genera/rivulidae/neofundulus.json"
    },
    {
      "Genus": "Notholebias",
      "SpeciesCount": 4,
      "genus_path": "genera/rivulidae/notholebias.json"
    },
    {
      "Genus": "Ophthalmolebias",
      "SpeciesCount": 1,
      "genus_path": "genera/rivulidae/ophthalmolebias.json"
    },
    {
      "Genus": "Papiliolebias",
      "SpeciesCount": 4,
      "genus_path": "genera/rivulidae/papiliolebias.json"
    },
    {
      "Genus": "Pituna",
      "SpeciesCount": 6,
      "genus_path": "genera/rivulidae/pituna.json"
    },
    {
      "Genus": "Plesiolebias",
      "SpeciesCount": 8,
      "genus_path": "genera/rivulidae/plesiolebias.json"
    },
    {
      "Genus": "Prorivulus",
      "SpeciesCount": 1,
      "genus_path": "genera/rivulidae/prorivulus.json"
    },
    {
      "Genus": "Pterolebias",
      "SpeciesCount": 4,
      "genus_path": "genera/rivulidae/pterolebias.json"
    },
    {
      "Genus": "Rachovia",
      "SpeciesCount": 5,
      "genus_path": "genera/rivulidae/rachovia.json"
    },
    {
      "Genus": "Renova",
      "SpeciesCount": 1,
      "genus_path": "genera/rivulidae/renova.json"
    },
    {
      "Genus": "Rivulus",
      "SpeciesCount": 12,
      "genus_path": "genera/rivulidae/rivulus.json"
    },
    {
      "Genus": "Simpsonichthys",
      "SpeciesCount": 25,
      "genus_path": "genera/rivulidae/simpsonichthys.json"
    },
    {
      "Genus": "Spectrolebias",
      "SpeciesCount": 9,
      "genus_path": "genera/rivulidae/spectrolebias.json"
    },
    {
      "Genus": "Stenolebias",
      "SpeciesCount": 2,
      "genus_path": "genera/rivulidae/stenolebias.json"
    },
    {
      "Genus": "Terranatos",
      "SpeciesCount": 1,
      "genus_path": "genera/rivulidae/terranatos.json"
    },
    {
      "Genus": "Trigonectes",
      "SpeciesCount": 6,
      "genus_path": "genera/rivulidae/trigonectes.json"
    },
    {
      "Genus": "Xenurolebias",
      "SpeciesCount": 4,
      "genus_path": "genera/rivulidae/xenurolebias.json"
    }
  ]
}