[
  {
    "ScientificName": "Eviota abax",
    "SpecCode": "23543",
    "CommonName": "Isohaze",
    "Environments": [
      "salt"
    ],
    "Subspecies": []
  },
  {
    "ScientificName": "Eviota afelei",
    "SpecCode": "7258",
    "CommonName": "Afele's dwarfgoby",
    "Environments": [
      "salt"
    ],
    "Subspecies": []
  },
  {
    "ScientificName": "Eviota albolineata",
    "SpecCode": "7259",
    "CommonName": "Bia",
    "Environments": [
      "salt"
    ],
    "Subspecies": []
  },
  {
    "ScientificName": "Eviota algida",
    "SpecCode": "67638",
    "CommonName": "Upwelling dwarfgoby",
    "Environments": [
      "salt"
    ],
    "Subspecies": []
  },
  {
    "ScientificName": "Eviota amamiko",
    "SpecCode": "70426",
    "CommonName": "Amamiko dwarfgoby",
    "Environments": [
      "salt"
    ],
    "Subspecies": []
  },
  {
    "ScientificName": "Eviota amphipora",
    "SpecCode": "69165",
    "CommonName": "Twinpore dwarfgoby",
    "Environments": [
      "salt"
    ],
    "Subspecies": []
  },
  {
    "ScientificName": "Eviota ancora",
    "SpecCode": "66016",
    "CommonName": "Bonbori-Isohaze",
    "Environments": [
      "salt"
    ],
    "Subspecies": []
  },
  {
    "ScientificName": "Eviota angustifascia",
    "SpecCode": "69461",
    "CommonName": "Whiteline dwarfgoby",
    "Environments": [
      "salt"
    ],
    "Subspecies": []
  },
  {
    "ScientificName": "Eviota aquila",
    "SpecCode": "67653",
    "CommonName": "Dark dwarfgoby",
    "Environments": [
      "salt"
    ],
    "Subspecies": []
  },
  {
    "ScientificName": "Eviota asymbasia",
    "SpecCode": "67955",
    "CommonName": "Inconsistent dwarfgoby",
    "Environments": [
      "salt"
    ],
    "Subspecies": []
  },
  {
    "ScientificName": "Eviota atriventris",
    "SpecCode": "66457",
    "CommonName": "Blackbelly dwarfgoby",
    "Environments": [
      "salt"
    ],
    "Subspecies": []
  },
  {
    "ScientificName": "Eviota bacata",
    "SpecCode": "70584",
    "CommonName": "Pearl dwarfgoby",
    "Environments": [
      "salt"
    ],
    "Subspecies": []
  },
  {
    "ScientificName": "Eviota bifasciata",
    "SpecCode": "7213",
    "CommonName": "Belukor",
    "Environments": [
      "salt"
    ],
    "Subspecies": []
  },
  {
    "ScientificName": "Eviota bilunula",
    "SpecCode": "68083",
    "CommonName": "Crescent dwarfgoby",
    "Environments": [
      "salt"
    ],
    "Subspecies": []
  },
  {
    "ScientificName": "Eviota bimaculata",
    "SpecCode": "59387",
    "CommonName": "Twin-occipital dwarfgoby",
    "Environments": [
      "salt"
    ],
    "Subspecies": []
  },
  {
    "ScientificName": "Eviota bipunctata",
    "SpecCode": "67956",
    "CommonName": "Twinspot dwarfgoby",
    "Environments": [
      "salt"
    ],
    "Subspecies": []
  },
  {
    "ScientificName": "Eviota brahmi",
    "SpecCode": "67334",
    "CommonName": "Brahm's dwarfgoby",
    "Environments": [
      "salt"
    ],
    "Subspecies": []
  },
  {
    "ScientificName": "Eviota cometa",
    "SpecCode": "7260",
    "CommonName": "Comet dwarfgoby",
    "Environments": [
      "salt"
    ],
    "Subspecies": []
  },
  {
    "ScientificName": "Eviota dalyi",
    "SpecCode": "69015",
    "CommonName": "Amirante dwarfgoby",
    "Environments": [
      "salt"
    ],
    "Subspecies": []
  },
  {
    "ScientificName": "Eviota deminuta",
    "SpecCode": "67174",
    "CommonName": "Diminutive dwarfgoby",
    "Environments": [
      "salt"
    ],
    "Subspecies": []
  },
  {
    "ScientificName": "Eviota disrupta",
    "SpecCode": "61063",
    "CommonName": "Brokenbar dwarfgoby",
    "Environments": [
      "salt"
    ],
    "Subspecies": []
  },
  {
    "ScientificName": "Eviota distigma",
    "SpecCode": "7261",
    "CommonName": "Distigma Eviota",
    "Environments": [
      "salt"
    ],
    "Subspecies": []
  },
  {
    "ScientificName": "Eviota dorsimaculata",
    "SpecCode": "67173",
    "CommonName": "Dorsal-spot dwarfgoby",
    "Environments": [
      "salt"
    ],
    "Subspecies": []
  },
  {
    "ScientificName": "Eviota dorsogilva",
    "SpecCode": "66243",
    "CommonName": "Creamback dwarfgoby",
    "Environments": [
      "salt"
    ],
    "Subspecies": []
  },
  {
    "ScientificName": "Eviota dorsopurpurea",
    "SpecCode": "66244",
    "CommonName": "Purple dwarfgoby",
    "Environments": [
      "salt"
    ],
    "Subspecies": []
  },
  {
    "ScientificName": "Eviota epiphanes",
    "SpecCode": "23544",
    "CommonName": "Divine dwarf goby",
    "Environments": [
      "salt"
    ],
    "Subspecies": []
  },
  {
    "ScientificName": "Eviota epistigmata",
    "SpecCode": "67701",
    "CommonName": "Twinspot drawfgoby",
    "Environments": [
      "salt"
    ],
    "Subspecies": []
  },
  {
    "ScientificName": "Eviota erdmanni",
    "SpecCode": "67959",
    "CommonName": "Erdmann's dwarfgoby",
    "Environments": [
      "salt"
    ],
    "Subspecies": []
  },
  {
    "ScientificName": "Eviota eyreae",
    "SpecCode": "67945",
    "CommonName": "Eyre's dwarfgoby",
    "Environments": [
      "salt"
    ],
    "Subspecies": []
  },
  {
    "ScientificName": "Eviota fallax",
    "SpecCode": "66631",
    "CommonName": "Twin Dwarfgoby",
    "Environments": [
      "salt"
    ],
    "Subspecies": []
  },
  {
    "ScientificName": "Eviota fasciola",
    "SpecCode": "7262",
    "CommonName": "Barred dwarfgoby",
    "Environments": [
      "salt"
    ],
    "Subspecies": []
  },
  {
    "ScientificName": "Eviota filamentosa",
    "SpecCode": "67975",
    "CommonName": "Itohiki-Isohaze",
    "Environments": [
      "salt"
    ],
    "Subspecies": []
  },
  {
    "ScientificName": "Eviota flaviarma",
    "SpecCode": "70425",
    "CommonName": "Yellow-shoulder dwarfgoby",
    "Environments": [
      "salt"
    ],
    "Subspecies": []
  },
  {
    "ScientificName": "Eviota flavipinnata",
    "SpecCode": "67964",
    "CommonName": "Kibire-isohaze",
    "Environments": [
      "salt"
    ],
    "Subspecies": []
  },
  {
    "ScientificName": "Eviota flebilis",
    "SpecCode": "67335",
    "CommonName": "Shizuki-Isohaze",
    "Environments": [
      "salt"
    ],
    "Subspecies": []
  },
  {
    "ScientificName": "Eviota geminata",
    "SpecCode": "67246",
    "CommonName": "Geminate dwarfgoby",
    "Environments": [
      "salt"
    ],
    "Subspecies": []
  },
  {
    "ScientificName": "Eviota gunawanae",
    "SpecCode": "68989",
    "CommonName": "Tiene's dwarfgoby",
    "Environments": [
      "salt"
    ],
    "Subspecies": []
  },
  {
    "ScientificName": "Eviota guttata",
    "SpecCode": "25452",
    "CommonName": "Green pygmy-goby",
    "Environments": [
      "salt"
    ],
    "Subspecies": []
  },
  {
    "ScientificName": "Eviota herrei",
    "SpecCode": "7263",
    "CommonName": "Herre's dwarfgoby",
    "Environments": [
      "salt"
    ],
    "Subspecies": []
  },
  {
    "ScientificName": "Eviota hinanoae",
    "SpecCode": "67167",
    "CommonName": "Hinano's dwarfgoby",
    "Environments": [
      "salt"
    ],
    "Subspecies": []
  },
  {
    "ScientificName": "Eviota hoesei",
    "SpecCode": "63881",
    "CommonName": "Doug's Eviota",
    "Environments": [
      "salt"
    ],
    "Subspecies": []
  },
  {
    "ScientificName": "Eviota imitata",
    "SpecCode": "68278",
    "CommonName": "Imitator dwarfgoby",
    "Environments": [
      "salt"
    ],
    "Subspecies": []
  },
  {
    "ScientificName": "Eviota indica",
    "SpecCode": "61329",
    "CommonName": "Indian dwarfgoby",
    "Environments": [
      "salt"
    ],
    "Subspecies": []
  },
  {
    "ScientificName": "Eviota infulata",
    "SpecCode": "7264",
    "CommonName": "Bia",
    "Environments": [
      "salt"
    ],
    "Subspecies": []
  },
  {
    "ScientificName": "Eviota inutilis",
    "SpecCode": "61330",
    "CommonName": "Chestspot dwarfgoby",
    "Environments": [
      "salt"
    ],
    "Subspecies": []
  },
  {
    "ScientificName": "Eviota irrasa",
    "SpecCode": "7632",
    "CommonName": "Bia",
    "Environments": [
      "salt"
    ],
    "Subspecies": []
  },
  {
    "ScientificName": "Eviota japonica",
    "SpecCode": "56753",
    "CommonName": "Japanese dwarfgoby",
    "Environments": [
      "salt"
    ],
    "Subspecies": []
  },
  {
    "ScientificName": "Eviota jewettae",
    "SpecCode": "66681",
    "CommonName": "Jewett's dwarfgoby",
    "Environments": [
      "salt"
    ],
    "Subspecies": []
  },
  {
    "ScientificName": "Eviota karaspila",
    "SpecCode": "65824",
    "CommonName": "Eastern headspot dwarfgoby",
    "Environments": [
      "salt"
    ],
    "Subspecies": []
  },
  {
    "ScientificName": "Eviota kermadecensis",
    "SpecCode": "66848",
    "CommonName": "Kermadec dwarfgoby",
    "Environments": [
      "salt"
    ],
    "Subspecies": []
  },
  {
    "ScientificName": "Eviota korechika",
    "SpecCode": "65013",
    "CommonName": "Korechika's dwarfoby",
    "Environments": [
      "salt"
    ],
    "Subspecies": []
  },
  {
    "ScientificName": "Eviota lachdeberei",
    "SpecCode": "7265",
    "CommonName": "Lachdebere's dwarfgoby",
    "Environments": [
      "salt"
    ],
    "Subspecies": []
  },
  {
    "ScientificName": "Eviota lacrimae",
    "SpecCode": "56861",
    "CommonName": "Teared dwarfgoby",
    "Environments": [
      "salt"
    ],
    "Subspecies": []
  },
  {
    "ScientificName": "Eviota lacrimosa",
    "SpecCode": "67171",
    "CommonName": "Weeping dwarfgoby",
    "Environments": [
      "salt"
    ],
    "Subspecies": []
  },
  {
    "ScientificName": "Eviota lateritea",
    "SpecCode": "67961",
    "CommonName": "Laterite dwarfgoby",
    "Environments": [
      "salt"
    ],
    "Subspecies": []
  },
  {
    "ScientificName": "Eviota latifasciata",
    "SpecCode": "7266",
    "CommonName": "Broad-banded pygmy goby",
    "Environments": [
      "salt"
    ],
    "Subspecies": []
  },
  {
    "ScientificName": "Eviota lentiginosa",
    "SpecCode": "68988",
    "CommonName": "Frecked dwarfgoby",
    "Environments": [
      "salt"
    ],
    "Subspecies": []
  },
  {
    "ScientificName": "Eviota longirostris",
    "SpecCode": "69759",
    "CommonName": "Long-snout dwarfgoby",
    "Environments": [
      "salt"
    ],
    "Subspecies": []
  },
  {
    "ScientificName": "Eviota maculibotella",
    "SpecCode": "67962",
    "CommonName": "Spotted dick dwarfgoby",
    "Environments": [
      "salt"
    ],
    "Subspecies": []
  },
  {
    "ScientificName": "Eviota maculosa",
    "SpecCode": "68987",
    "CommonName": "Polkadot dwarfgoby",
    "Environments": [
      "salt"
    ],
    "Subspecies": []
  },
  {
    "ScientificName": "Eviota marerubrum",
    "SpecCode": "69760",
    "CommonName": "Red Sea dwarfgoby",
    "Environments": [
      "salt"
    ],
    "Subspecies": []
  },
  {
    "ScientificName": "Eviota marteynae",
    "SpecCode": "69166",
    "CommonName": "Red star-eye dwarfgoby",
    "Environments": [
      "salt"
    ],
    "Subspecies": []
  },
  {
    "ScientificName": "Eviota masudai",
    "SpecCode": "64547",
    "CommonName": "Aka-isohaze",
    "Environments": [
      "salt"
    ],
    "Subspecies": []
  },
  {
    "ScientificName": "Eviota melanosphena",
    "SpecCode": "67957",
    "CommonName": "Wedge dwarfgoby",
    "Environments": [
      "salt"
    ],
    "Subspecies": []
  },
  {
    "ScientificName": "Eviota melasma",
    "SpecCode": "7267",
    "CommonName": "Akahoshi-isohaze",
    "Environments": [
      "salt"
    ],
    "Subspecies": []
  },
  {
    "ScientificName": "Eviota mikiae",
    "SpecCode": "61035",
    "CommonName": "Miki's dwarfgoby",
    "Environments": [
      "salt"
    ],
    "Subspecies": []
  },
  {
    "ScientificName": "Eviota mimica",
    "SpecCode": "67946",
    "CommonName": "Mimic dwarfgoby",
    "Environments": [
      "salt"
    ],
    "Subspecies": []
  },
  {
    "ScientificName": "Eviota minuta",
    "SpecCode": "67549",
    "CommonName": "Minute dwarfgoby",
    "Environments": [
      "salt"
    ],
    "Subspecies": []
  },
  {
    "ScientificName": "Eviota monostigma",
    "SpecCode": "62210",
    "CommonName": "Singlespot dwarfgoby",
    "Environments": [
      "salt"
    ],
    "Subspecies": []
  },
  {
    "ScientificName": "Eviota natalis",
    "SpecCode": "65018",
    "CommonName": "Christmas dwarfgoby",
    "Environments": [
      "salt"
    ],
    "Subspecies": []
  },
  {
    "ScientificName": "Eviota nebulosa",
    "SpecCode": "7268",
    "CommonName": "Nebulous dwarfgoby",
    "Environments": [
      "salt"
    ],
    "Subspecies": []
  },
  {
    "ScientificName": "Eviota nigramembrana",
    "SpecCode": "66963",
    "CommonName": "Blackbar dwarfgoby",
    "Environments": [
      "salt"
    ],
    "Subspecies": []
  },
  {
    "ScientificName": "Eviota nigripinna",
    "SpecCode": "25461",
    "CommonName": "Blackfin dwarfgoby",
    "Environments": [
      "salt"
    ],
    "Subspecies": []
  },
  {
    "ScientificName": "Eviota nigrispina",
    "SpecCode": "65814",
    "CommonName": "Blackspine dwarfgoby",
    "Environments": [
      "salt"
    ],
    "Subspecies": []
  },
  {
    "ScientificName": "Eviota nigriventris",
    "SpecCode": "7214",
    "CommonName": "Bia",
    "Environments": [
      "salt"
    ],
    "Subspecies": []
  },
  {
    "ScientificName": "Eviota notata",
    "SpecCode": "66625",
    "CommonName": "Barhead dwarfgoby",
    "Environments": [
      "salt"
    ],
    "Subspecies": []
  },
  {
    "ScientificName": "Eviota occasa",
    "SpecCode": "67262",
    "CommonName": "Kijimunaa-isohaze",
    "Environments": [
      "salt"
    ],
    "Subspecies": []
  },
  {
    "ScientificName": "Eviota ocellifer",
    "SpecCode": "65014",
    "CommonName": "Ocellated dwarfgoby",
    "Environments": [
      "brackish",
      "salt"
    ],
    "Subspecies": []
  },
  {
    "ScientificName": "Eviota oculineata",
    "SpecCode": "69761",
    "CommonName": "False-comet dwarfgoby",
    "Environments": [
      "salt"
    ],
    "Subspecies": []
  },
  {
    "ScientificName": "Eviota oculopiperita",
    "SpecCode": "67245",
    "CommonName": "Pepperminteye dwarfgoby",
    "Environments": [
      "salt"
    ],
    "Subspecies": []
  },
  {
    "ScientificName": "Eviota pamae",
    "SpecCode": "67272",
    "CommonName": "Pam's dwarfgoby",
    "Environments": [
      "salt"
    ],
    "Subspecies": []
  },
  {
    "ScientificName": "Eviota pardalota",
    "SpecCode": "46398",
    "CommonName": "Leopard dwarfgoby",
    "Environments": [
      "salt"
    ],
    "Subspecies": []
  },
  {
    "ScientificName": "Eviota partimacula",
    "SpecCode": "64273",
    "CommonName": "Dividedspot dwarfgoby",
    "Environments": [
      "salt"
    ],
    "Subspecies": []
  },
  {
    "ScientificName": "Eviota pellucida",
    "SpecCode": "7269",
    "CommonName": "Belukor",
    "Environments": [
      "salt"
    ],
    "Subspecies": []
  },
  {
    "ScientificName": "Eviota perspicilla",
    "SpecCode": "70427",
    "CommonName": "Glasses dwarfgoby",
    "Environments": [
      "salt"
    ],
    "Subspecies": []
  },
  {
    "ScientificName": "Eviota pictifacies",
    "SpecCode": "68274",
    "CommonName": "Paintedface dwarfgoby",
    "Environments": [
      "salt"
    ],
    "Subspecies": []
  },
  {
    "ScientificName": "Eviota pinocchioi",
    "SpecCode": "66683",
    "CommonName": "Pinocchio dwarfgoby",
    "Environments": [
      "salt"
    ],
    "Subspecies": []
  },
  {
    "ScientificName": "Eviota piperata",
    "SpecCode": "67244",
    "CommonName": "Peppered dwarfgoby",
    "Environments": [
      "salt"
    ],
    "Subspecies": []
  },
  {
    "ScientificName": "Eviota prasina",
    "SpecCode": "7270",
    "CommonName": "Bia",
    "Environments": [
      "salt"
    ],
    "Subspecies": []
  },
  {
    "ScientificName": "Eviota prasites",
    "SpecCode": "7271",
    "CommonName": "Ao-isohaze",
    "Environments": [
      "salt"
    ],
    "Subspecies": []
  },
  {
    "ScientificName": "Eviota pseudaprica",
    "SpecCode": "69128",
    "CommonName": "False sunny dwarfgoby",
    "Environments": [
      "salt"
    ],
    "Subspecies": []
  },
  {
    "ScientificName": "Eviota pseudostigma",
    "SpecCode": "62211",
    "CommonName": "False singlespot dwarfgoby",
    "Environments": [
      "salt"
    ],
    "Subspecies": []
  },
  {
    "ScientificName": "Eviota pseudozebrina",
    "SpecCode": "69758",
    "CommonName": "Fijian zebra dwarfgoby",
    "Environments": [
      "salt"
    ],
    "Subspecies": []
  },
  {
    "ScientificName": "Eviota punctulata",
    "SpecCode": "7272",
    "CommonName": "Bia",
    "Environments": [
      "salt"
    ],
    "Subspecies": []
  },
  {
    "ScientificName": "Eviota punyit",
    "SpecCode": "68283",
    "CommonName": "Punyit dwarfgoby",
    "Environments": [
      "salt"
    ],
    "Subspecies": []
  },
  {
    "ScientificName": "Eviota queenslandica",
    "SpecCode": "7273",
    "CommonName": "Bia",
    "Environments": [
      "salt"
    ],
    "Subspecies": []
  },
  {
    "ScientificName": "Eviota raja",
    "SpecCode": "61033",
    "CommonName": "King dwarfgoby",
    "Environments": [
      "salt"
    ],
    "Subspecies": []
  },
  {
    "ScientificName": "Eviota randalli",
    "SpecCode": "65416",
    "CommonName": "Randall's dwarfgoby",
    "Environments": [
      "salt"
    ],
    "Subspecies": []
  },
  {
    "ScientificName": "Eviota readerae",
    "SpecCode": "63884",
    "CommonName": "Reader's dwarfgoby",
    "Environments": [
      "salt"
    ],
    "Subspecies": []
  },
  {
    "ScientificName": "Eviota richardi",
    "SpecCode": "67947",
    "CommonName": "Rick's dwarfgoby",
    "Environments": [
      "salt"
    ],
    "Subspecies": []
  },
  {
    "ScientificName": "Eviota rubra",
    "SpecCode": "68281",
    "CommonName": "Red dwarfgoby",
    "Environments": [
      "salt"
    ],
    "Subspecies": []
  },
  {
    "ScientificName": "Eviota rubriceps",
    "SpecCode": "66375",
    "CommonName": "Redhead dwarfgoby",
    "Environments": [
      "salt"
    ],
    "Subspecies": []
  },
  {
    "ScientificName": "Eviota rubriguttata",
    "SpecCode": "66017",
    "CommonName": "Hanabi-Isohaze",
    "Environments": [
      "salt"
    ],
    "Subspecies": []
  },
  {
    "ScientificName": "Eviota rubrimaculata",
    "SpecCode": "68282",
    "CommonName": "Redspot dwarfgoby",
    "Environments": [
      "salt"
    ],
    "Subspecies": []
  },
  {
    "ScientificName": "Eviota rubrisparsa",
    "SpecCode": "65432",
    "CommonName": "Redspeckled dwarfgoby",
    "Environments": [
      "salt"
    ],
    "Subspecies": []
  },
  {
    "ScientificName": "Eviota saipanensis",
    "SpecCode": "7274",
    "CommonName": "Saipan dwarfgoby",
    "Environments": [
      "salt"
    ],
    "Subspecies": []
  },
  {
    "ScientificName": "Eviota santanai",
    "SpecCode": "67212",
    "CommonName": "Santana's dwarfgoby",
    "Environments": [
      "salt"
    ],
    "Subspecies": []
  },
  {
    "ScientificName": "Eviota sebreei",
    "SpecCode": "7275",
    "CommonName": "Bia",
    "Environments": [
      "salt"
    ],
    "Subspecies": []
  },
  {
    "ScientificName": "Eviota shibukawai",
    "SpecCode": "67974",
    "CommonName": "Akabana-Isohaze",
    "Environments": [
      "salt"
    ],
    "Subspecies": []
  },
  {
    "ScientificName": "Eviota shimadai",
    "SpecCode": "65431",
    "CommonName": "Shimadai's dwarfgoby",
    "Environments": [
      "salt"
    ],
    "Subspecies": []
  },
  {
    "ScientificName": "Eviota sigillata",
    "SpecCode": "7276",
    "CommonName": "Adorned dwarfgoby",
    "Environments": [
      "salt"
    ],
    "Subspecies": []
  },
  {
    "ScientificName": "Eviota singula",
    "SpecCode": "67963",
    "CommonName": "One-spot dwarfgoby",
    "Environments": [
      "salt"
    ],
    "Subspecies": []
  },
  {
    "ScientificName": "Eviota smaragdus",
    "SpecCode": "11170",
    "CommonName": "Emerald dwarfgoby",
    "Environments": [
      "salt"
    ],
    "Subspecies": []
  },
  {
    "ScientificName": "Eviota sodwanaensis",
    "SpecCode": "68026",
    "CommonName": "Sodwana dwarfgoby",
    "Environments": [
      "salt"
    ],
    "Subspecies": []
  },
  {
    "ScientificName": "Eviota sparsa",
    "SpecCode": "7635",
    "CommonName": "Bia",
    "Environments": [
      "salt"
    ],
    "Subspecies": []
  },
  {
    "ScientificName": "Eviota specca",
    "SpecCode": "67336",
    "CommonName": "Dusted dwarfgoby",
    "Environments": [
      "salt"
    ],
    "Subspecies": []
  },
  {
    "ScientificName": "Eviota spilota",
    "SpecCode": "7638",
    "CommonName": "Bia",
    "Environments": [
      "salt"
    ],
    "Subspecies": []
  },
  {
    "ScientificName": "Eviota springeri",
    "SpecCode": "66626",
    "CommonName": "Springer's Dwarfgoby",
    "Environments": [
      "salt"
    ],
    "Subspecies": []
  },
  {
    "ScientificName": "Eviota storthynx",
    "SpecCode": "7639",
    "CommonName": "Belly-spotted pygmy-goby",
    "Environments": [
      "salt"
    ],
    "Subspecies": []
  },
  {
    "ScientificName": "Eviota susanae",
    "SpecCode": "58217",
    "CommonName": "Susan's dwarfgoby",
    "Environments": [
      "salt"
    ],
    "Subspecies": []
  },
  {
    "ScientificName": "Eviota taeiae",
    "SpecCode": "70118",
    "CommonName": "Taei's Dwarfgoby",
    "Environments": [
      "salt"
    ],
    "Subspecies": []
  },
  {
    "ScientificName": "Eviota teresae",
    "SpecCode": "67948",
    "CommonName": "Terry's dwarfgoby",
    "Environments": [
      "salt"
    ],
    "Subspecies": []
  },
  {
    "ScientificName": "Eviota tetha",
    "SpecCode": "67676",
    "CommonName": "Tetha's dwarfgoby",
    "Environments": [
      "salt"
    ],
    "Subspecies": []
  },
  {
    "ScientificName": "Eviota thamani",
    "SpecCode": "67950",
    "CommonName": "Thaman's dwarfgoby",
    "Environments": [
      "salt"
    ],
    "Subspecies": []
  },
  {
    "ScientificName": "Eviota tigrina",
    "SpecCode": "64746",
    "CommonName": "Tiger dwarfgoby",
    "Environments": [
      "salt"
    ],
    "Subspecies": []
  },
  {
    "ScientificName": "Eviota toshiyuki",
    "SpecCode": "65429",
    "CommonName": "Midorihaze",
    "Environments": [
      "salt"
    ],
    "Subspecies": []
  },
  {
    "ScientificName": "Eviota variola",
    "SpecCode": "65015",
    "CommonName": "Finspot dwarfgoby",
    "Environments": [
      "salt"
    ],
    "Subspecies": []
  },
  {
    "ScientificName": "Eviota winterbottomi",
    "SpecCode": "65430",
    "CommonName": "Duskybar dwarfgoby",
    "Environments": [
      "salt"
    ],
    "Subspecies": []
  },
  {
    "ScientificName": "Eviota zebrina",
    "SpecCode": "25462",
    "CommonName": "Five-bar pygmy-goby",
    "Environments": [
      "brackish",
      "salt"
    ],
    "Subspecies": []
  },
  {
    "ScientificName": "Eviota zonura",
    "SpecCode": "22459",
    "CommonName": "Greenbanded eviota",
    "Environments": [
      "salt"
    ],
    "Subspecies": []
  }
]