[
  {
    "ScientificName": "Tropheops biriwira",
    "SpecCode": "68968",
    "CommonName": null,
    "Environments": [
      "fresh"
    ],
    "Subspecies": []
  },
  {
    "ScientificName": "Tropheops gracilior",
    "SpecCode": "8342",
    "CommonName": "Chalunda",
    "Environments": [
      "fresh"
    ],
    "Subspecies": []
  },
  {
    "ScientificName": "Tropheops kamtambo",
    "SpecCode": "68969",
    "CommonName": null,
    "Environments": [
      "fresh"
    ],
    "Subspecies": []
  },
  {
    "ScientificName": "Tropheops kumwera",
    "SpecCode": "68967",
    "CommonName": null,
    "Environments": [
      "fresh"
    ],
    "Subspecies": []
  },
  {
    "ScientificName": "Tropheops lucerna",
    "SpecCode": "2375",
    "CommonName": "Mbuna",
    "Environments": [
      "fresh"
    ],
    "Subspecies": []
  },
  {
    "ScientificName": "Tropheops macrophthalmus",
    "SpecCode": "2376",
    "CommonName": "Großaugenmaulbrüter",
    "Environments": [
      "fresh"
    ],
    "Subspecies": []
  },
  {
    "ScientificName": "Tropheops microstoma",
    "SpecCode": "2377",
    "CommonName": "Mbuna",
    "Environments": [
      "fresh"
    ],
    "Subspecies": []
  },
  {
    "ScientificName": "Tropheops modestus",
    "SpecCode": "8339",
    "CommonName": "Mbuna",
    "Environments": [
      "fresh"
    ],
    "Subspecies": []
  },
  {
    "ScientificName": "Tropheops novemfasciatus",
    "SpecCode": "2379",
    "CommonName": "Mbuna",
    "Environments": [
      "fresh"
    ],
    "Subspecies": []
  },
  {
    "ScientificName": "Tropheops romandi",
    "SpecCode": "8343",
    "CommonName": "Mbuna",
    "Environments": [
      "fresh"
    ],
    "Subspecies": []
  },
  {
    "ScientificName": "Tropheops tropheops",
    "SpecCode": "2381",
    "CommonName": "Abiti alabi",
    "Environments": [
      "fresh"
    ],
    "Subspecies": []
  }
]