[
  {
    "ScientificName": "Schizodon altoparanae",
    "SpecCode": "52644",
    "CommonName": "Parana-bredbundkigger",
    "Environments": [
      "fresh"
    ],
    "Subspecies": []
  },
  {
    "ScientificName": "Schizodon australis",
    "SpecCode": "52645",
    "CommonName": "Sydlig bredbundkigger",
    "Environments": [
      "fresh"
    ],
    "Subspecies": []
  },
  {
    "ScientificName": "Schizodon borellii",
    "SpecCode": "53266",
    "CommonName": "Aracú pintado",
    "Environments": [
      "fresh"
    ],
    "Subspecies": []
  },
  {
    "ScientificName": "Schizodon corti",
    "SpecCode": "48614",
    "CommonName": "Cotí",
    "Environments": [
      "fresh"
    ],
    "Subspecies": []
  },
  {
    "ScientificName": "Schizodon dissimilis",
    "SpecCode": "57584",
    "CommonName": "Piau galo",
    "Environments": [
      "fresh"
    ],
    "Subspecies": []
  },
  {
    "ScientificName": "Schizodon fasciatus",
    "SpecCode": "23448",
    "CommonName": "Acurupintado",
    "Environments": [
      "fresh"
    ],
    "Subspecies": []
  },
  {
    "ScientificName": "Schizodon intermedius",
    "SpecCode": "52646",
    "CommonName": "Højrygget bundkigger",
    "Environments": [
      "fresh"
    ],
    "Subspecies": []
  },
  {
    "ScientificName": "Schizodon isognathus",
    "SpecCode": "53275",
    "CommonName": "Cuiaba bredbundkigger",
    "Environments": [
      "fresh"
    ],
    "Subspecies": []
  },
  {
    "ScientificName": "Schizodon jacuiensis",
    "SpecCode": "52647",
    "CommonName": "Lagunebundkigger",
    "Environments": [
      "fresh"
    ],
    "Subspecies": []
  },
  {
    "ScientificName": "Schizodon knerii",
    "SpecCode": "53725",
    "CommonName": "Bahia-bredbundkigger",
    "Environments": [
      "fresh"
    ],
    "Subspecies": []
  },
  {
    "ScientificName": "Schizodon nasutus",
    "SpecCode": "53264",
    "CommonName": "Amboré",
    "Environments": [
      "fresh"
    ],
    "Subspecies": []
  },
  {
    "ScientificName": "Schizodon platae",
    "SpecCode": "53265",
    "CommonName": "Boga lisa",
    "Environments": [
      "fresh"
    ],
    "Subspecies": []
  },
  {
    "ScientificName": "Schizodon rostratus",
    "SpecCode": "61627",
    "CommonName": "Teresina-bredbundkigger",
    "Environments": [
      "fresh"
    ],
    "Subspecies": []
  },
  {
    "ScientificName": "Schizodon scotorhabdotus",
    "SpecCode": "64031",
    "CommonName": "Mørkstribet bredbundkigger",
    "Environments": [
      "fresh"
    ],
    "Subspecies": []
  },
  {
    "ScientificName": "Schizodon succinctus",
    "SpecCode": "66127",
    "CommonName": "Rosario-bredbundkigger",
    "Environments": [
      "fresh"
    ],
    "Subspecies": []
  },
  {
    "ScientificName": "Schizodon vittatus",
    "SpecCode": "25712",
    "CommonName": "Aracu",
    "Environments": [
      "fresh"
    ],
    "Subspecies": []
  }
]