[
  {
    "ScientificName": "Rasboroides nigromarginatus",
    "SpecCode": "68384",
    "CommonName": null,
    "Environments": [
      "fresh"
    ],
    "Subspecies": []
  },
  {
    "ScientificName": "Rasboroides pallidus",
    "SpecCode": "68373",
    "CommonName": "Pallidus rasbora",
    "Environments": [
      "fresh"
    ],
    "Subspecies": []
  },
  {
    "ScientificName": "Rasboroides rohani",
    "SpecCode": "68385",
    "CommonName": null,
    "Environments": [
      "fresh"
    ],
    "Subspecies": []
  },
  {
    "ScientificName": "Rasboroides vaterifloris",
    "SpecCode": "6148",
    "CommonName": "Blauer Perlmuttbärbling",
    "Environments": [
      "fresh"
    ],
    "Subspecies": []
  }
]